roboclaw_python-0.10.2.dist-info/METADATA
roboclaw_python-0.10.2.dist-info/WHEEL
roboclaw_python.libs/libgcc_s-02f3f192.so.1
roboclaw_python/__init__.py
roboclaw_python/__init__.pyi
roboclaw_python/py.typed
roboclaw_python/roboclaw_python.abi3.so
roboclaw_python-0.10.2.dist-info/RECORD
