Metadata-Version: 2.4
Name: roboclaw_python
Version: 0.10.2
